.hgignore
.installed.cfg
.project
.pydevproject
LICENSE
MANIFEST.in
README.txt
bootstrap.py
buildout.cfg
setup.py
bin/buildout
docs/HISTORY.txt
docs/README.txt
src/ztfy/__init__.py
src/ztfy.security.egg-info/PKG-INFO
src/ztfy.security.egg-info/SOURCES.txt
src/ztfy.security.egg-info/dependency_links.txt
src/ztfy.security.egg-info/namespace_packages.txt
src/ztfy.security.egg-info/not-zip-safe
src/ztfy.security.egg-info/requires.txt
src/ztfy.security.egg-info/top_level.txt
src/ztfy/security/README.txt
src/ztfy/security/__init__.py
src/ztfy/security/configure.zcml
src/ztfy/security/database.py
src/ztfy/security/indexer.py
src/ztfy/security/interfaces.py
src/ztfy/security/property.py
src/ztfy/security/schema.py
src/ztfy/security/search.py
src/ztfy/security/security.py
src/ztfy/security/auth/__init__.py
src/ztfy/security/auth/configure.zcml
src/ztfy/security/auth/token.py
src/ztfy/security/auth/token.txt
src/ztfy/security/browser/__init__.py
src/ztfy/security/browser/configure.zcml
src/ztfy/security/browser/roles.py
src/ztfy/security/browser/json/__init__.py
src/ztfy/security/browser/json/configure.zcml
src/ztfy/security/browser/json/search.py
src/ztfy/security/browser/widget/__init__.py
src/ztfy/security/browser/widget/configure.zcml
src/ztfy/security/browser/widget/interfaces.py
src/ztfy/security/browser/widget/principal.py
src/ztfy/security/browser/widget/templates/principal_display.pt
src/ztfy/security/browser/widget/templates/principal_input.pt
src/ztfy/security/browser/widget/templates/principal_list_display.pt
src/ztfy/security/browser/widget/templates/principal_list_input.pt
src/ztfy/security/doctests/README.txt
src/ztfy/security/locales/ztfy.security.pot
src/ztfy/security/locales/en/LC_MESSAGES/ztfy.security.mo
src/ztfy/security/locales/en/LC_MESSAGES/ztfy.security.po
src/ztfy/security/locales/fr/LC_MESSAGES/ztfy.security.mo
src/ztfy/security/locales/fr/LC_MESSAGES/ztfy.security.po
src/ztfy/security/tal/__init__.py
src/ztfy/security/tal/api.py
src/ztfy/security/tal/configure.zcml
src/ztfy/security/tal/interfaces.py
src/ztfy/security/tests/__init__.py
src/ztfy/security/tests/test_securitydocs.py
src/ztfy/security/tests/test_securitydocstrings.py